{"Squash":{"StartDate":"2019-03-12","EndDate":"2019-04-14","Ladders":{"Ladder":[{"Number":"1","Players":{"Name":["Adrian Brace","Adrian Fisk","Joshua Davies","Phil Maybury","Wynford Davies"]}},{"Number":"2","Players":{"Name":["Lloyd Newland","Rich Timms","Ben Howcroft","Joe Powell","Mark Turner"]}},{"Number":"3","Players":{"Name":["Sam Norris","Jon Bennett","Steve Evans","Dylan Vite","Steve Melhuish"]}},{"Number":4,"Players":{"Name":["Cameron Docherty","Jonathon Young","Marcus Docherty","Josh Llewelyn","Cian Grathidge"]}},{"Number":5,"Players":{"Name":["Chris Jones","Ashley Maybury","Aran Norris","Mike Hurst","Taylur Gauci"]}},{"Number":6,"Players":{"Name":["Steve Jones","Jack Penberthy","Shivam Singhal","Mark Morgan","Lucy Maybury"]}},{"Number":7,"Players":{"Name":["Rares Ciurezu","Ben Kwaitkowski","Tom Gordon","James Pickett","Luke Jones"]}},{"Number":8,"Players":{"Name":["Matt Lane","Keith McCarthy","Anthony Greaves","Jayesh Parmar"]}}]}},"Racketball":{"StartDate":"2019-03-12","EndDate":"2019-04-14","Ladders":{"Ladder":[{"Number":1,"Players":{"Name":["Tim Curtis","Dave Mason","Tony Jones","Ray Skene","Jonathan Young","Chris Emanuel","Brian Starks","Neil Watkins","Chris Yates","Simon Griffin","Steve Thomas","Chris Jones","Jon Bennett","Erica Howcroft","Nigel Bevan"]}}]}}}